{"ohlcv": {"2026-05-14": {"open": 57.3, "high": 57.6, "low": 56.8, "close": 57.4, "vol": 11219.0}, "2026-05-15": {"open": 59.3, "high": 59.3, "low": 55.0, "close": 55.2, "vol": 12185.0}, "2026-05-18": {"open": 53.7, "high": 55.0, "low": 52.1, "close": 55.0, "vol": 9219.0}, "2026-05-19": {"open": 55.7, "high": 56.3, "low": 54.1, "close": 55.5, "vol": 6362.0}, "2026-05-20": {"open": 56.4, "high": 58.0, "low": 55.5, "close": 57.9, "vol": 12580.0}, "2026-05-21": {"open": 62.8, "high": 63.6, "low": 61.5, "close": 63.6, "vol": 31136.0}, "2026-05-22": {"open": 65.5, "high": 69.9, "low": 65.4, "close": 69.9, "vol": 28941.0}, "2026-05-25": {"open": 75.9, "high": 76.8, "low": 75.9, "close": 76.8, "vol": 12450.0}, "2026-05-26": {"open": 84.4, "high": 84.4, "low": 84.4, "close": 84.4, "vol": 22123.0}, "2026-05-27": {"open": 85.4, "high": 92.8, "low": 79.3, "close": 90.2, "vol": 208873.0}, "2026-05-28": {"open": 90.2, "high": 99.2, "low": 89.5, "close": 90.7, "vol": 16979.0}, "2026-05-29": {"open": 99.0, "high": 99.7, "low": 96.0, "close": 99.5, "vol": 14442.0}, "2026-06-01": {"open": 100.0, "high": 101.5, "low": 96.6, "close": 97.0, "vol": 9584.0}, "2026-06-02": {"open": 96.6, "high": 96.6, "low": 87.3, "close": 90.1, "vol": 14509.0}, "2026-06-03": {"open": 92.3, "high": 96.9, "low": 92.3, "close": 96.9, "vol": 8885.0}, "2026-06-04": {"open": 94.0, "high": 94.3, "low": 89.9, "close": 90.9, "vol": 4477.0}, "2026-06-05": {"open": 86.0, "high": 87.5, "low": 83.3, "close": 85.5, "vol": 10974.0}, "2026-06-08": {"open": 77.0, "high": 80.0, "low": 77.0, "close": 80.0, "vol": 13314.0}, "2026-06-09": {"open": 83.0, "high": 88.0, "low": 81.7, "close": 87.2, "vol": 9653.0}, "2026-06-10": {"open": 85.5, "high": 89.4, "low": 78.5, "close": 78.5, "vol": 8674.0}, "2026-06-11": {"open": 79.5, "high": 80.9, "low": 71.7, "close": 80.9, "vol": 10832.0}, "2026-06-12": {"open": 88.9, "high": 88.9, "low": 87.0, "close": 88.9, "vol": 9017.0}, "2026-06-15": {"open": 94.2, "high": 97.7, "low": 94.2, "close": 97.7, "vol": 7347.0}, "2026-06-16": {"open": 104.0, "high": 107.0, "low": 103.0, "close": 107.0, "vol": 18899.0}, "2026-06-17": {"open": 107.0, "high": 117.5, "low": 103.5, "close": 114.0, "vol": 170656.0}, "2026-06-18": {"open": 119.5, "high": 122.0, "low": 110.0, "close": 120.0, "vol": 114043.0}, "2026-06-22": {"open": 121.0, "high": 123.0, "low": 115.0, "close": 116.5, "vol": 81507.0}, "2026-06-23": {"open": 114.0, "high": 118.0, "low": 109.0, "close": 114.5, "vol": 66025.0}, "2026-06-24": {"open": 112.0, "high": 116.5, "low": 106.5, "close": 116.0, "vol": 44962.0}, "2026-06-25": {"open": 116.0, "high": 127.5, "low": 114.0, "close": 125.0, "vol": 151017.0}, "2026-06-26": {"open": 126.0, "high": 134.5, "low": 119.0, "close": 119.5, "vol": 139283.0}, "2026-06-29": {"open": 122.5, "high": 123.0, "low": 109.5, "close": 112.0, "vol": 78415.0}, "2026-06-30": {"open": 119.5, "high": 123.0, "low": 118.5, "close": 123.0, "vol": 23572.0}, "2026-07-01": {"open": 135.0, "high": 135.0, "low": 135.0, "close": 135.0, "vol": 30229.0}, "2026-07-02": {"open": 135.5, "high": 148.5, "low": 135.0, "close": 148.5, "vol": 79538.0}, "2026-07-03": {"open": 153.0, "high": 163.0, "low": 147.0, "close": 163.0, "vol": 196306.0}, "2026-07-06": {"open": 168.5, "high": 174.0, "low": 154.5, "close": 156.0, "vol": 182998.0}, "2026-07-07": {"open": 153.5, "high": 153.5, "low": 140.5, "close": 145.5, "vol": 110430.0}, "2026-07-08": {"open": 149.0, "high": 160.0, "low": 145.0, "close": 160.0, "vol": 137662.0}, "2026-07-09": {"open": 161.0, "high": 175.0, "low": 159.0, "close": 172.5, "vol": 180809.0}, "2026-07-10": {"open": 172.5, "high": 172.5, "low": 172.5, "close": 172.5, "vol": 0.0}, "2026-07-13": {"open": 189.5, "high": 189.5, "low": 185.5, "close": 189.5, "vol": 70076.0}, "2026-07-14": {"open": 185.0, "high": 194.5, "low": 171.0, "close": 186.5, "vol": 175885.0}, "2026-07-15": {"open": 187.5, "high": 189.0, "low": 175.0, "close": 179.5, "vol": 116995.0}, "2026-07-16": {"open": 174.5, "high": 184.0, "low": 165.0, "close": 166.0, "vol": 108857.0}, "2026-07-17": {"open": 150.5, "high": 156.5, "low": 149.5, "close": 149.5, "vol": 57016.0}}, "margin": {"2026-05-14": {"fin_diff": 0, "fin_bal": 38526, "short_diff": 0, "short_bal": 1134}, "2026-05-15": {"fin_diff": 0, "fin_bal": 36655, "short_diff": 0, "short_bal": 1145}, "2026-05-18": {"fin_diff": -886, "fin_bal": 35769, "short_diff": -184, "short_bal": 961}, "2026-05-19": {"fin_diff": -337, "fin_bal": 35432, "short_diff": 21, "short_bal": 982}, "2026-05-20": {"fin_diff": 2983, "fin_bal": 38415, "short_diff": 82, "short_bal": 1064}, "2026-05-21": {"fin_diff": 9604, "fin_bal": 48019, "short_diff": 51, "short_bal": 1115}, "2026-05-22": {"fin_diff": 5772, "fin_bal": 53791, "short_diff": 87, "short_bal": 1202}, "2026-05-25": {"fin_diff": 281, "fin_bal": 54072, "short_diff": 0, "short_bal": 1202}, "2026-05-26": {"fin_diff": 1325, "fin_bal": 55397, "short_diff": 661, "short_bal": 1863}, "2026-05-27": {"fin_diff": 5474, "fin_bal": 60871, "short_diff": 3531, "short_bal": 5394}, "2026-05-28": {"fin_diff": -270, "fin_bal": 60601, "short_diff": -2265, "short_bal": 3129}, "2026-05-29": {"fin_diff": -1007, "fin_bal": 59594, "short_diff": -1235, "short_bal": 1894}, "2026-06-01": {"fin_diff": -1281, "fin_bal": 58313, "short_diff": -24, "short_bal": 1870}, "2026-06-02": {"fin_diff": -2287, "fin_bal": 56026, "short_diff": -41, "short_bal": 1829}, "2026-06-03": {"fin_diff": -721, "fin_bal": 55305, "short_diff": 141, "short_bal": 1970}, "2026-06-04": {"fin_diff": -516, "fin_bal": 54789, "short_diff": 72, "short_bal": 2042}, "2026-06-05": {"fin_diff": -578, "fin_bal": 54211, "short_diff": -126, "short_bal": 1916}, "2026-06-08": {"fin_diff": -6141, "fin_bal": 48070, "short_diff": 0, "short_bal": 1916}, "2026-06-09": {"fin_diff": -589, "fin_bal": 47481, "short_diff": 412, "short_bal": 2328}, "2026-06-10": {"fin_diff": -1377, "fin_bal": 46104, "short_diff": 108, "short_bal": 2436}, "2026-06-11": {"fin_diff": -2041, "fin_bal": 44063, "short_diff": -108, "short_bal": 2328}, "2026-06-12": {"fin_diff": -73, "fin_bal": 43990, "short_diff": 203, "short_bal": 2531}, "2026-06-15": {"fin_diff": 617, "fin_bal": 44607, "short_diff": 90, "short_bal": 2621}, "2026-06-16": {"fin_diff": 1683, "fin_bal": 46290, "short_diff": 634, "short_bal": 3255}, "2026-06-17": {"fin_diff": 9818, "fin_bal": 56108, "short_diff": 2295, "short_bal": 5550}, "2026-06-18": {"fin_diff": 4080, "fin_bal": 60188, "short_diff": 317, "short_bal": 5867}, "2026-06-22": {"fin_diff": -321, "fin_bal": 59867, "short_diff": -78, "short_bal": 5789}, "2026-06-23": {"fin_diff": 3327, "fin_bal": 63194, "short_diff": -2223, "short_bal": 3566}, "2026-06-24": {"fin_diff": 472, "fin_bal": 63666, "short_diff": -1194, "short_bal": 2372}, "2026-06-25": {"fin_diff": 623, "fin_bal": 64289, "short_diff": -430, "short_bal": 1942}, "2026-06-26": {"fin_diff": -2484, "fin_bal": 61805, "short_diff": -80, "short_bal": 1862}, "2026-06-29": {"fin_diff": -4107, "fin_bal": 57698, "short_diff": -201, "short_bal": 1661}, "2026-06-30": {"fin_diff": 6808, "fin_bal": 64506, "short_diff": 200, "short_bal": 1861}, "2026-07-01": {"fin_diff": 482, "fin_bal": 64988, "short_diff": 70, "short_bal": 1931}, "2026-07-02": {"fin_diff": 3849, "fin_bal": 68837, "short_diff": 1072, "short_bal": 3003}, "2026-07-03": {"fin_diff": -40, "fin_bal": 68797, "short_diff": 1227, "short_bal": 4230}, "2026-07-06": {"fin_diff": -4485, "fin_bal": 64312, "short_diff": -822, "short_bal": 3408}, "2026-07-07": {"fin_diff": -2137, "fin_bal": 62175, "short_diff": -922, "short_bal": 2486}, "2026-07-08": {"fin_diff": 5623, "fin_bal": 67798, "short_diff": 773, "short_bal": 3259}, "2026-07-09": {"fin_diff": 7230, "fin_bal": 75028, "short_diff": 1191, "short_bal": 4450}, "2026-07-10": {"fin_diff": 0, "fin_bal": null, "short_diff": 0, "short_bal": null}, "2026-07-13": {"fin_diff": -2057, "fin_bal": 72971, "short_diff": -239, "short_bal": 4211}, "2026-07-14": {"fin_diff": 2658, "fin_bal": 75629, "short_diff": -781, "short_bal": 3430}, "2026-07-15": {"fin_diff": -96, "fin_bal": 75533, "short_diff": 35, "short_bal": 3465}, "2026-07-16": {"fin_diff": -2263, "fin_bal": 73270, "short_diff": -255, "short_bal": 3210}, "2026-07-17": {"fin_diff": -9260, "fin_bal": 64010, "short_diff": 653, "short_bal": 3863}}, "lending": {"2026-05-14": {"lend_sell": 0, "lend_ret": -1004, "lend_bal": 21440.0}, "2026-05-15": {"lend_sell": 0, "lend_ret": -415, "lend_bal": 21025.0}, "2026-05-18": {"lend_sell": 0, "lend_ret": -291, "lend_bal": 20734.0}, "2026-05-19": {"lend_sell": 0, "lend_ret": -971, "lend_bal": 19763.0}, "2026-05-20": {"lend_sell": 0, "lend_ret": -21, "lend_bal": 19742.0}, "2026-05-21": {"lend_sell": 0, "lend_ret": -13, "lend_bal": 19729.0}, "2026-05-22": {"lend_sell": 0, "lend_ret": -286, "lend_bal": 19443.0}, "2026-05-25": {"lend_sell": 0, "lend_ret": -30, "lend_bal": 19413.0}, "2026-05-26": {"lend_sell": 103, "lend_ret": 0, "lend_bal": 19516.0}, "2026-05-27": {"lend_sell": 2183, "lend_ret": 0, "lend_bal": 21699.0}, "2026-05-28": {"lend_sell": 163, "lend_ret": 0, "lend_bal": 21862.0}, "2026-05-29": {"lend_sell": 0, "lend_ret": -841, "lend_bal": 21021.0}, "2026-06-01": {"lend_sell": 0, "lend_ret": -877, "lend_bal": 20144.0}, "2026-06-02": {"lend_sell": 0, "lend_ret": -1334, "lend_bal": 18810.0}, "2026-06-03": {"lend_sell": 145, "lend_ret": 0, "lend_bal": 18955.0}, "2026-06-04": {"lend_sell": 0, "lend_ret": -97, "lend_bal": 18858.0}, "2026-06-05": {"lend_sell": 519, "lend_ret": 0, "lend_bal": 19377.0}, "2026-06-08": {"lend_sell": 153, "lend_ret": 0, "lend_bal": 19530.0}, "2026-06-09": {"lend_sell": 318, "lend_ret": 0, "lend_bal": 19848.0}, "2026-06-10": {"lend_sell": 70, "lend_ret": 0, "lend_bal": 19918.0}, "2026-06-11": {"lend_sell": 0, "lend_ret": 0, "lend_bal": 0.0}, "2026-06-12": {"lend_sell": 0, "lend_ret": -657, "lend_bal": 19412.0}, "2026-06-15": {"lend_sell": 0, "lend_ret": -41, "lend_bal": 19370.0}, "2026-06-16": {"lend_sell": 135, "lend_ret": 0, "lend_bal": 19505.0}, "2026-06-17": {"lend_sell": 1482, "lend_ret": 0, "lend_bal": 20987.0}, "2026-06-18": {"lend_sell": 592, "lend_ret": 0, "lend_bal": 21578.0}, "2026-06-22": {"lend_sell": 168, "lend_ret": 0, "lend_bal": 21746.0}, "2026-06-23": {"lend_sell": 0, "lend_ret": -3274, "lend_bal": 18472.0}, "2026-06-24": {"lend_sell": 0, "lend_ret": -5856, "lend_bal": 12616.0}, "2026-06-25": {"lend_sell": 3391, "lend_ret": 0, "lend_bal": 16007.0}, "2026-06-26": {"lend_sell": 4004, "lend_ret": 0, "lend_bal": 20011.0}, "2026-06-29": {"lend_sell": 3919, "lend_ret": 0, "lend_bal": 23930.0}, "2026-06-30": {"lend_sell": 1048, "lend_ret": 0, "lend_bal": 24978.0}, "2026-07-01": {"lend_sell": 0, "lend_ret": -440, "lend_bal": 24538.0}, "2026-07-02": {"lend_sell": 1318, "lend_ret": 0, "lend_bal": 25856.0}, "2026-07-03": {"lend_sell": 0, "lend_ret": -385, "lend_bal": 25471.0}, "2026-07-06": {"lend_sell": 0, "lend_ret": -213, "lend_bal": 25258.0}, "2026-07-07": {"lend_sell": 2319, "lend_ret": 0, "lend_bal": 27577.0}, "2026-07-08": {"lend_sell": 0, "lend_ret": -1267, "lend_bal": 26310.0}, "2026-07-09": {"lend_sell": 2627, "lend_ret": 0, "lend_bal": 28937.0}, "2026-07-10": {"lend_sell": 0, "lend_ret": 0, "lend_bal": null}, "2026-07-13": {"lend_sell": 525, "lend_ret": 0, "lend_bal": 29462.0}, "2026-07-14": {"lend_sell": 0, "lend_ret": -69, "lend_bal": 29393.0}, "2026-07-15": {"lend_sell": 688, "lend_ret": 0, "lend_bal": 30081.0}, "2026-07-16": {"lend_sell": 0, "lend_ret": -666, "lend_bal": 29415.0}, "2026-07-17": {"lend_sell": 0, "lend_ret": -23, "lend_bal": 29392.0}}, "inst": {"2026-05-14": {"foreign": 0, "trust": 0, "dealer": 0}, "2026-05-15": {"foreign": 1796.2, "trust": 0.0, "dealer": -212.0}, "2026-05-18": {"foreign": 1263.0, "trust": 0.0, "dealer": -95.5}, "2026-05-19": {"foreign": 688.0, "trust": 0.0, "dealer": 54.8}, "2026-05-20": {"foreign": 459.9, "trust": 0.0, "dealer": 115.6}, "2026-05-21": {"foreign": 641.3, "trust": 0.0, "dealer": 3548.9}, "2026-05-22": {"foreign": 1486.4, "trust": 0.0, "dealer": 3426.3}, "2026-05-25": {"foreign": 485.9, "trust": 0.0, "dealer": 608.1}, "2026-05-26": {"foreign": -93.0, "trust": 231.0, "dealer": 40.8}, "2026-05-27": {"foreign": 16103.8, "trust": 5558.0, "dealer": -487.0}, "2026-05-28": {"foreign": -2877.2, "trust": 0.0, "dealer": -49.5}, "2026-05-29": {"foreign": 2801.6, "trust": 123.0, "dealer": -666.0}, "2026-06-01": {"foreign": 837.7, "trust": 0.0, "dealer": -389.0}, "2026-06-02": {"foreign": 1077.7, "trust": 0.0, "dealer": 171.2}, "2026-06-03": {"foreign": 3470.3, "trust": 0.0, "dealer": -525.0}, "2026-06-04": {"foreign": 629.0, "trust": 0.0, "dealer": -169.0}, "2026-06-05": {"foreign": -1908.0, "trust": 0.0, "dealer": 327.4}, "2026-06-08": {"foreign": 909.0, "trust": 0.0, "dealer": -489.0}, "2026-06-09": {"foreign": 1027.6, "trust": 0.0, "dealer": -804.0}, "2026-06-10": {"foreign": 384.1, "trust": 0.0, "dealer": -1027.8}, "2026-06-11": {"foreign": 2055.9, "trust": 0.0, "dealer": 473.8}, "2026-06-12": {"foreign": 880.5, "trust": 0.0, "dealer": 128.3}, "2026-06-15": {"foreign": 745.9, "trust": 0.0, "dealer": -64.3}, "2026-06-16": {"foreign": 1057.7, "trust": 89.0, "dealer": 45.2}, "2026-06-17": {"foreign": -2329.1, "trust": 6335.0, "dealer": -272.5}, "2026-06-18": {"foreign": -3203.6, "trust": 2688.0, "dealer": 2266.4}, "2026-06-22": {"foreign": -13901.6, "trust": 566.0, "dealer": -335.2}, "2026-06-23": {"foreign": -3769.8, "trust": 9.0, "dealer": -457.5}, "2026-06-24": {"foreign": -1820.1, "trust": 0.0, "dealer": -869.4}, "2026-06-25": {"foreign": 4475.5, "trust": 3545.0, "dealer": -2279.7}, "2026-06-26": {"foreign": -6165.0, "trust": 3903.0, "dealer": -5602.1}, "2026-06-29": {"foreign": -6206.8, "trust": 2728.0, "dealer": -426.0}, "2026-06-30": {"foreign": -670.8, "trust": 0.0, "dealer": 400.7}, "2026-07-01": {"foreign": -378.0, "trust": 0.0, "dealer": 556.5}, "2026-07-02": {"foreign": 19334.2, "trust": -189.0, "dealer": -978.9}, "2026-07-03": {"foreign": 3798.4, "trust": 5371.0, "dealer": -1553.3}, "2026-07-06": {"foreign": -5504.3, "trust": 2226.0, "dealer": -498.4}, "2026-07-07": {"foreign": 401.0, "trust": -1740.0, "dealer": -872.6}, "2026-07-08": {"foreign": -7663.6, "trust": 1184.0, "dealer": 1174.1}, "2026-07-09": {"foreign": 7080.0, "trust": 4216.0, "dealer": 350.4}, "2026-07-10": {"foreign": 0, "trust": 0, "dealer": 0}, "2026-07-13": {"foreign": 4087.1, "trust": 1938.0, "dealer": 0.9}, "2026-07-14": {"foreign": -7060.5, "trust": -1878.0, "dealer": -1114.9}, "2026-07-15": {"foreign": -4177.3, "trust": -648.0, "dealer": 192.0}, "2026-07-16": {"foreign": -1827.8, "trust": -32.0, "dealer": -17.5}, "2026-07-17": {"foreign": 2370.5, "trust": 202.0, "dealer": -2089.7}}, "stock_id": "6182", "last_date": "20260717", "generated_ymd": "20260719"}